graph/__init__.py
graph/adjacency_matrix.py
graph/all_pairs_shortest_path.py
graph/all_paths.py
graph/all_simple_paths.py
graph/assignment_problem.py
graph/base.py
graph/bfs.py
graph/core.py
graph/critical_path.py
graph/cycle.py
graph/dag.py
graph/degree_of_separation.py
graph/dfs.py
graph/distance_map.py
graph/finite_state_machine.py
graph/hash_methods.py
graph/max_flow.py
graph/max_flow_min_cut.py
graph/maximum_flow_min_cut.py
graph/min_cost_flow.py
graph/minmax.py
graph/minsum.py
graph/partite.py
graph/random.py
graph/shortest_path.py
graph/shortest_tree_all_pairs.py
graph/topological_sort.py
graph/traffic_scheduling_problem.py
graph/transshipment_problem.py
graph/tsp.py
graph/version.py
graph/visuals.py
graph_theory-2023.7.8.data/data/LICENSE
graph_theory-2023.7.8.data/data/README.md
graph_theory-2023.7.8.data/data/requirements.txt
graph_theory-2023.7.8.dist-info/LICENSE
graph_theory-2023.7.8.dist-info/METADATA
graph_theory-2023.7.8.dist-info/WHEEL
graph_theory-2023.7.8.dist-info/top_level.txt
graph_theory-2023.7.8.dist-info/RECORD
