Metadata-Version: 2.2
Name: graph-theory
Version: 2023.7.8
Summary: A graph library
Home-page: https://github.com/root-11/graph-theory
Author: https://github.com/root-11
License: MIT
Keywords: adjacency,adjacent,algorithms,all pairs shortest path,analysis,assignment problem,complex-networks,component,components,congestions,critical,critical-path,cycle,discrete mathematics,finite,finite state machine,flow,flow-problem,fsm,generate,generation,graph,Graph Theory,graph-algorithms,graph-analysis,graph-generation,graph-hash,graph-theory,graph-visualization,graphs,hash,hash-tree,hill-climbing,jam,machine,math,Mathematics,maths,matrix,merkle,merkle-tree,method,minimise,minimize,mini
Platform: any
Classifier: Development Status :: 5 - Production/Stable
Classifier: Intended Audience :: Science/Research
Classifier: Natural Language :: English
Classifier: License :: OSI Approved :: MIT License
Classifier: Programming Language :: Python :: 3.8
Classifier: Programming Language :: Python :: 3.9
Classifier: Programming Language :: Python :: 3.10
Classifier: Programming Language :: Python :: 3.11
Classifier: Programming Language :: Python :: 3.12
Requires-Python: >=3.8
License-File: LICENSE
Dynamic: author
Dynamic: classifier
Dynamic: description
Dynamic: description-content-type
Dynamic: home-page
Dynamic: keywords
Dynamic: license
Dynamic: platform
Dynamic: requires-python
Dynamic: summary
